netscript/__init__.py
netscript/app.py
netscript/run_class.py
netscript_grey_liedtke-0.0.3.dist-info/licenses/LICENSE
netscript_grey_liedtke-0.0.3.dist-info/METADATA
netscript_grey_liedtke-0.0.3.dist-info/WHEEL
netscript_grey_liedtke-0.0.3.dist-info/top_level.txt
netscript_grey_liedtke-0.0.3.dist-info/RECORD
