Metadata-Version: 2.4
Name: netscript_grey.liedtke
Version: 0.0.3
Summary: A small example package
Author: Grey Liedtke
Author-email: Grey Liedtke <grey.liedtke@example.com>
License-Expression: MIT
Project-URL: Homepage, https://github.com/pypa/sampleproject
Project-URL: Issues, https://github.com/pypa/sampleproject/issues
Classifier: Programming Language :: Python :: 3
Classifier: Operating System :: OS Independent
Requires-Python: >=3.9
License-File: LICENSE
Dynamic: author
Dynamic: license-file
